tfpy/core/group.py
tfpy/core/interpolation.py
tfpy/core/stack.py
tfpy/main.py
tfpy-0.6.0.dist-info/entry_points.txt
tfpy-0.6.0.dist-info/LICENSE
tfpy-0.6.0.dist-info/WHEEL
tfpy-0.6.0.dist-info/METADATA
tfpy-0.6.0.dist-info/RECORD
