Metadata-Version: 2.1
Name: tfpy
Version: 0.6.0
Summary: Create Terraform resources using Python
Home-page: https://rgreinho.github.io/tfpy
License: MIT
Keywords: terraform
Author: Rémy Greinhofer
Author-email: remy.greinhofer@gmail.com
Requires-Python: >=3.7,<4.0
Classifier: Development Status :: 5 - Production/Stable
Classifier: Environment :: Console
Classifier: Intended Audience :: End Users/Desktop
Classifier: License :: OSI Approved :: MIT License
Classifier: Operating System :: MacOS :: MacOS X
Classifier: Operating System :: Microsoft :: Windows
Classifier: Operating System :: POSIX :: Linux
Classifier: Programming Language :: Python
Classifier: Programming Language :: Python :: 3
Classifier: Programming Language :: Python :: 3 :: Only
Classifier: Programming Language :: Python :: 3.7
Classifier: Programming Language :: Python :: 3.8
Classifier: Topic :: Utilities
Requires-Dist: loguru (>=0.4.1,<0.5.0)
Requires-Dist: pyyaml (>=5.3.1,<6.0.0)
Requires-Dist: terraformpy (==1.3.0)
Requires-Dist: typer (>=0.2.1,<0.3.0)
Project-URL: Documentation, https://rgreinho.github.io/tfpy
Project-URL: Repository, https://github.com/rgreinho/tfpy
